CHANGES.rst
CONTRIBUTORS.rst
MANIFEST.in
README.rst
bootstrap.py
buildout.cfg
setup.py
cpskin/__init__.py
cpskin.diazotheme.memory.egg-info/PKG-INFO
cpskin.diazotheme.memory.egg-info/SOURCES.txt
cpskin.diazotheme.memory.egg-info/dependency_links.txt
cpskin.diazotheme.memory.egg-info/entry_points.txt
cpskin.diazotheme.memory.egg-info/namespace_packages.txt
cpskin.diazotheme.memory.egg-info/not-zip-safe
cpskin.diazotheme.memory.egg-info/requires.txt
cpskin.diazotheme.memory.egg-info/top_level.txt
cpskin/diazotheme/__init__.py
cpskin/diazotheme/memory/__init__.py
cpskin/diazotheme/memory/configure.zcml
cpskin/diazotheme/memory/profiles.zcml
cpskin/diazotheme/memory/profiles/default/cssregistry.xml
cpskin/diazotheme/memory/profiles/default/jsregistry.xml
cpskin/diazotheme/memory/profiles/default/lessregistry.xml
cpskin/diazotheme/memory/profiles/default/metadata.xml
cpskin/diazotheme/memory/profiles/default/theme.xml
cpskin/diazotheme/memory/profiles/uninstall/cssregistry.xml
cpskin/diazotheme/memory/profiles/uninstall/jsregistry.xml
cpskin/diazotheme/memory/profiles/uninstall/lessregistry.xml
cpskin/diazotheme/memory/static/manifest.cfg
cpskin/diazotheme/memory/static/preview.png
cpskin/diazotheme/memory/static/rules.xml
cpskin/diazotheme/memory/static/css/styles.css
cpskin/diazotheme/memory/static/images/footer-bg.png
cpskin/diazotheme/memory/static/images/organization-picto-hover.png
cpskin/diazotheme/memory/static/images/organization-picto.png
cpskin/diazotheme/memory/static/images/personne-picto-hover.png
cpskin/diazotheme/memory/static/images/personne-picto.png
cpskin/diazotheme/memory/static/images/picture-icon.png
cpskin/diazotheme/memory/static/images/video-icon.png
cpskin/diazotheme/memory/static/js/cpskin_memory.js
cpskin/diazotheme/memory/static/less/mobile.less
cpskin/diazotheme/memory/static/less/mobilelarge.less
cpskin/diazotheme/memory/static/less/styles.less
cpskin/diazotheme/memory/static/less/variables.less
cpskin/diazotheme/memory/static/rules/footer.xml
cpskin/diazotheme/memory/static/rules/header.xml
docs/LICENSE.GPL
docs/LICENSE.rst